app/.gitkeep
app/app.py
app/http_errors.py
app/settings.py
app/tags_metadata.py
app/controllers/__init__.py
app/controllers/auth.py
app/models/__init__.py
app/models/base.py
app/models/event.py
app/models/journey.py
app/models/organization.py
app/models/persona.py
app/models/project.py
app/models/tool.py
app/models/tool_call.py
app/models/user.py
app/routers/.gitkeep
app/routers/__init__.py
app/routers/utilities.py
app/routers/v1/__init__.py
app/routers/v1/organizations.py
app/routers/v1/auth/README.md
app/routers/v1/auth/__Init__.py
app/routers/v1/auth/google.py
app/routers/v1/auth/jwt.py
app/routers/v1/auth/username_password.py
langstory-0.0.1.dist-info/METADATA
langstory-0.0.1.dist-info/WHEEL
langstory-0.0.1.dist-info/top_level.txt
langstory-0.0.1.dist-info/RECORD
